climada_petals/__init__.py
climada_petals/_version.py
climada_petals/conf/climada.conf
climada_petals/data/crop_production/FAOSTAT_data_producer_prices.csv
climada_petals/data/crop_production/FAOSTAT_data_production_quantity.csv
climada_petals/data/crop_production/crop_production_demo_data_cultivated_area_CHE.nc4
climada_petals/data/crop_production/crop_production_demo_data_yields_CHE.nc4
climada_petals/data/crop_production/hist_mean_mai-firr_1976-2005_DE_FR.hdf5
climada_petals/data/crop_production/histsoc_landuse-15crops_annual_FR_DE_DEMO_2001_2005.nc
climada_petals/data/gdp_asset/GDP2Asset_converter_2.5arcmin.nc
climada_petals/data/gdp_asset/gdp2asset_CHE_exposure.nc
climada_petals/data/relative_cropyield/gepic_gfdl-esm2m_ewembi_historical_2005soc_co2_yield-whe-noirr_global_DEMO_TJANJIN_annual_1861_2005.nc
climada_petals/data/relative_cropyield/lpjml_ipsl-cm5a-lr_ewembi_historical_2005soc_co2_yield-whe-noirr_annual_FR_DE_DEMO_1861_2005.nc
climada_petals/data/relative_cropyield/pepic_miroc5_ewembi_historical_2005soc_co2_yield-whe-firr_global_annual_DEMO_TJANJIN_1861_2005.nc
climada_petals/data/relative_cropyield/pepic_miroc5_ewembi_historical_2005soc_co2_yield-whe-noirr_global_annual_DEMO_TJANJIN_1861_2005.nc
climada_petals/data/river_flood/flddph_2000_DEMO.nc
climada_petals/data/river_flood/fldfrc_2000_DEMO.nc
climada_petals/data/tc_surge_bathtub/SRTM15+V2.0_sample.tiff
climada_petals/data/wildfire/Portugal_firms_2016_17_18_MODIS.csv
climada_petals/data/wildfire/Portugal_firms_June_2017.csv
climada_petals/engine/__init__.py
climada_petals/engine/warn.py
climada_petals/engine/supplychain/__init__.py
climada_petals/engine/supplychain/core.py
climada_petals/engine/supplychain/mriot_handling.py
climada_petals/engine/supplychain/utils.py
climada_petals/engine/supplychain/test/test_core.py
climada_petals/engine/supplychain/test/test_mriot_handling.py
climada_petals/engine/supplychain/test/test_utils.py
climada_petals/engine/test/__init__.py
climada_petals-6.1.0.dist-info/licenses/AUTHORS.md
climada_petals-6.1.0.dist-info/licenses/LICENSE
climada_petals-6.1.0.dist-info/METADATA
climada_petals-6.1.0.dist-info/WHEEL
climada_petals-6.1.0.dist-info/top_level.txt
climada_petals-6.1.0.dist-info/RECORD
