Metadata-Version: 2.4
Name: climada_petals
Version: 6.1.0
Summary: CLIMADA Extensions
Author-email: ETH <climada-info@sympa.ethz.ch>
License: GNU General Public License v3 (GPLv3)
Project-URL: Homepage, https://github.com/CLIMADA-project/climada_petals
Keywords: climate,adaptation
Classifier: Development Status :: 4 - Beta
Classifier: Programming Language :: Python :: 3
Classifier: Topic :: Scientific/Engineering :: Atmospheric Science
Classifier: Topic :: Scientific/Engineering :: GIS
Classifier: Topic :: Scientific/Engineering :: Mathematics
Requires-Python: <3.13,>=3.10
License-File: LICENSE
License-File: AUTHORS.md
Requires-Dist: boario
Requires-Dist: climada>=6.1
Requires-Dist: cdsapi
Requires-Dist: osm-flex
Requires-Dist: pymrio
Requires-Dist: rioxarray
Requires-Dist: ruamel.yaml
Requires-Dist: scikit-image
Requires-Dist: xesmf
Dynamic: license-file
